Metadata-Version: 2.1
Name: xbos-services-utils3
Version: 0.0.1.dev3
Summary: Utility functions for xbos service using Python 3.6.
Home-page: UNKNOWN
Author: Daniel Lengyel
Author-email: daniel.lengyel@berkeley.edu
License: UNKNOWN
Platform: UNKNOWN
